trytond/modules/health_stock_nursing/COPYING
trytond/modules/health_stock_nursing/README.rst
trytond/modules/health_stock_nursing/__init__.py
trytond/modules/health_stock_nursing/data/messages/messages.xml
trytond/modules/health_stock_nursing/exceptions.py
trytond/modules/health_stock_nursing/health_stock_nursing.py
trytond/modules/health_stock_nursing/health_stock_nursing_view.xml
trytond/modules/health_stock_nursing/locale/ar.po
trytond/modules/health_stock_nursing/locale/de.po
trytond/modules/health_stock_nursing/locale/el.po
trytond/modules/health_stock_nursing/locale/eo.po
trytond/modules/health_stock_nursing/locale/es.po
trytond/modules/health_stock_nursing/locale/fr.po
trytond/modules/health_stock_nursing/locale/health_stock_nursing.pot
trytond/modules/health_stock_nursing/locale/it_IT.po
trytond/modules/health_stock_nursing/locale/ja_JP.po
trytond/modules/health_stock_nursing/locale/ka.po
trytond/modules/health_stock_nursing/locale/lo.po
trytond/modules/health_stock_nursing/locale/pt_BR.po
trytond/modules/health_stock_nursing/locale/sv.po
trytond/modules/health_stock_nursing/locale/tr.po
trytond/modules/health_stock_nursing/locale/uk.po
trytond/modules/health_stock_nursing/locale/zh_CN.po
trytond/modules/health_stock_nursing/pyproject.toml
trytond/modules/health_stock_nursing/tests/__init__.py
trytond/modules/health_stock_nursing/tests/test_health_stock_nursing.py
trytond/modules/health_stock_nursing/tryton.cfg
trytond/modules/health_stock_nursing/view/ambulatory_care_form.xml
trytond/modules/health_stock_nursing/view/gnuhealth_ambulatory_care_medical_supplies_tree.xml
trytond/modules/health_stock_nursing/view/gnuhealth_ambulatory_care_medicament_form.xml
trytond/modules/health_stock_nursing/view/gnuhealth_ambulatory_care_medicament_tree.xml
trytond/modules/health_stock_nursing/view/gnuhealth_patient_ambulatory_care_tree.xml
gnuhealth_stock_nursing-5.0.2.dist-info/METADATA
gnuhealth_stock_nursing-5.0.2.dist-info/WHEEL
gnuhealth_stock_nursing-5.0.2.dist-info/licenses/COPYING
gnuhealth_stock_nursing-5.0.2.dist-info/RECORD
